src/__init__.py
src/auth.py
src/cli.py
src/server.py
src/adapters/__init__.py
src/adapters/client.py
src/submodule/ticktick-py/oauth.py
src/submodule/ticktick-py/setup.py
src/submodule/ticktick-py/tests/__init__.py
src/submodule/ticktick-py/tests/conftest.py
src/submodule/ticktick-py/tests/integration/__init__.py
src/submodule/ticktick-py/tests/integration/test_api.py
src/submodule/ticktick-py/tests/integration/test_oauth2.py
src/submodule/ticktick-py/tests/integration/test_projects.py
src/submodule/ticktick-py/tests/integration/test_tags.py
src/submodule/ticktick-py/tests/integration/test_tasks.py
src/submodule/ticktick-py/tests/unit/__init__.py
src/submodule/ticktick-py/tests/unit/test_api.py
src/submodule/ticktick-py/tests/unit/test_cache_handler.py
src/submodule/ticktick-py/tests/unit/test_hex_color_creator.py
src/submodule/ticktick-py/tests/unit/test_oauth2.py
src/submodule/ticktick-py/tests/unit/test_tasks.py
src/submodule/ticktick-py/tests/unit/test_time_zone.py
src/submodule/ticktick-py/ticktick/__init__.py
src/submodule/ticktick-py/ticktick/api.py
src/submodule/ticktick-py/ticktick/cache.py
src/submodule/ticktick-py/ticktick/oauth2.py
src/submodule/ticktick-py/ticktick/helpers/__init__.py
src/submodule/ticktick-py/ticktick/helpers/constants.py
src/submodule/ticktick-py/ticktick/helpers/hex_color.py
src/submodule/ticktick-py/ticktick/helpers/time_methods.py
src/submodule/ticktick-py/ticktick/managers/__init__.py
src/submodule/ticktick-py/ticktick/managers/check_logged_in.py
src/submodule/ticktick-py/ticktick/managers/focus.py
src/submodule/ticktick-py/ticktick/managers/habits.py
src/submodule/ticktick-py/ticktick/managers/pomo.py
src/submodule/ticktick-py/ticktick/managers/projects.py
src/submodule/ticktick-py/ticktick/managers/settings.py
src/submodule/ticktick-py/ticktick/managers/tags.py
src/submodule/ticktick-py/ticktick/managers/tasks.py
src/tools/__init__.py
src/tools/auth.py
src/tools/projects.py
src/tools/tasks.py
src/utils/__init__.py
ticktick_mcp_v2-1.0.5.dist-info/licenses/LICENSE
ticktick_mcp_v2-1.0.5.dist-info/METADATA
ticktick_mcp_v2-1.0.5.dist-info/WHEEL
ticktick_mcp_v2-1.0.5.dist-info/entry_points.txt
ticktick_mcp_v2-1.0.5.dist-info/top_level.txt
ticktick_mcp_v2-1.0.5.dist-info/RECORD
