Metadata-Version: 2.4
Name: ticktick-mcp-v2
Version: 1.0.5
Summary: TickTick MCP Server - Enhanced Version with Chinese Support
Author-email: TickTick MCP Team <dev@example.com>
License: MIT
Project-URL: Homepage, https://github.com/example/ticktick-mcp-v2
Project-URL: Repository, https://github.com/example/ticktick-mcp-v2
Project-URL: Issues, https://github.com/example/ticktick-mcp-v2/issues
Keywords: ticktick,mcp,model-context-protocol,task-management
Classifier: Development Status :: 5 - Production/Stable
Classifier: Intended Audience :: Developers
Classifier: License :: OSI Approved :: MIT License
Classifier: Programming Language :: Python :: 3
Classifier: Programming Language :: Python :: 3.10
Classifier: Programming Language :: Python :: 3.11
Classifier: Programming Language :: Python :: 3.12
Classifier: Topic :: Office/Business :: Scheduling
Classifier: Topic :: Software Development :: Libraries :: Python Modules
Requires-Python: >=3.10
License-File: LICENSE
Requires-Dist: mcp>=1.0.0
Requires-Dist: pandas>=2.2.0
Requires-Dist: numpy>=1.24.0
Requires-Dist: pytz>=2023.3
Requires-Dist: python-dateutil>=2.8.2
Requires-Dist: python-dotenv>=1.0.0
Requires-Dist: httpx>=0.24.0
Requires-Dist: requests>=2.31.0
Requires-Dist: pydantic>=2.0.0
Requires-Dist: click>=8.0.0
Requires-Dist: nest-asyncio>=1.5.0
Requires-Dist: pytest-asyncio>=1.1.0
Provides-Extra: dev
Requires-Dist: pytest>=7.4.0; extra == "dev"
Requires-Dist: pytest-cov>=4.1.0; extra == "dev"
Requires-Dist: ruff>=0.1.0; extra == "dev"
Requires-Dist: build>=0.10.0; extra == "dev"
Requires-Dist: twine>=4.0.0; extra == "dev"
Dynamic: license-file
